lumpyrem/__init__.py
lumpyrem/lr2series.py
lumpyrem/lumprem.py
lumpyrem/lumprep.py
lumpyrem/pest.py
lumpyrem/run.py
lumpyrem-0.1.3.dist-info/LICENSE
lumpyrem-0.1.3.dist-info/METADATA
lumpyrem-0.1.3.dist-info/WHEEL
lumpyrem-0.1.3.dist-info/top_level.txt
lumpyrem-0.1.3.dist-info/RECORD
