Metadata-Version: 2.1
Name: lumpyrem
Version: 0.1.3
Summary: This package reads, writes and runs LUMPREM2 and associated utility programs
Home-page: https://github.com/rhugman/lumpyrem
Author: Rui Hugman
Author-email: rthugman@gmail.com
Classifier: Programming Language :: Python :: 3
Classifier: License :: OSI Approved :: MIT License
Classifier: Operating System :: OS Independent
Requires-Python: >=3.6
License-File: LICENSE
